fr/__init__.py
fr/ansi.py
fr/darwin.py
fr/linux.py
fr/meta.py
fr/utils.py
fr/windows.py
fr-3.0.data/scripts/fr
fr-3.0.dist-info/LICENSE
fr-3.0.dist-info/METADATA
fr-3.0.dist-info/WHEEL
fr-3.0.dist-info/top_level.txt
fr-3.0.dist-info/RECORD
